mapel/roommates/__init__.py
mapel/roommates/cultures_.py
mapel/roommates/distances_.py
mapel/roommates/features_.py
mapel/roommates/cultures/__init__.py
mapel/roommates/cultures/_utils.py
mapel/roommates/cultures/euclidean.py
mapel/roommates/cultures/group_separable.py
mapel/roommates/cultures/impartial.py
mapel/roommates/cultures/mallows.py
mapel/roommates/cultures/urn.py
mapel/roommates/distances/__init__.py
mapel/roommates/distances/main_distances.py
mapel/roommates/features/__init__.py
mapel/roommates/features/basic_features.py
mapel/roommates/features/distance_to_stability_features.py
mapel/roommates/objects/Roommates.py
mapel/roommates/objects/RoommatesExperiment.py
mapel/roommates/objects/RoommatesFamily.py
mapel/roommates/objects/__init__.py
mapel/roommates/persistence/__init__.py
mapel/roommates/persistence/instance_exports.py
mapel/roommates/persistence/instance_imports.py
mapel_roommates-2.1.11.dist-info/LICENSE.txt
mapel_roommates-2.1.11.dist-info/METADATA
mapel_roommates-2.1.11.dist-info/WHEEL
mapel_roommates-2.1.11.dist-info/top_level.txt
mapel_roommates-2.1.11.dist-info/RECORD
